<?xml version="1.0" encoding="UTF-8" standalone="yes"?><sst xmlns="http://schemas.openxmlformats.org/spreadsheetml/2006/main" count="13" uniqueCount="13"><si><t>Id calcule</t><phoneticPr fontId="1" type="noConversion"/></si><si><t>Source</t><phoneticPr fontId="1" type="noConversion"/></si><si><t>Poste 1</t><phoneticPr fontId="1" type="noConversion"/></si><si><t>Longueur</t><phoneticPr fontId="1" type="noConversion"/></si><si><t>Section cable</t><phoneticPr fontId="1" type="noConversion"/></si><si><t>Niveau tension</t><phoneticPr fontId="1" type="noConversion"/></si><si><t>Coefficient</t><phoneticPr fontId="1" type="noConversion"/></si><si><t>Puissance point</t><phoneticPr fontId="1" type="noConversion"/></si><si><t>Puissance cumulee</t><phoneticPr fontId="1" type="noConversion"/></si><si><t>Intensite</t><phoneticPr fontId="1" type="noConversion"/></si><si><t>Chute tension</t><phoneticPr fontId="1" type="noConversion"/></si><si><t>Delta cumulee</t><phoneticPr fontId="1" type="noConversion"/></si><si><t>Delta U</t><phoneticPr fontId="1" type="noConversion"/></si></sst>